{
  "level_id": "level-0166",
  "chapter_id": "chapter-004",
  "idiom_ids": [
    "idiom-00204",
    "idiom-00421",
    "idiom-00493",
    "idiom-00492"
  ],
  "board_width": 6,
  "board_height": 7,
  "candidate_chars": [
    "万",
    "不",
    "得",
    "已",
    "能",
    "自",
    "严",
    "于",
    "律",
    "己"
  ],
  "layout_profile": "chain-4",
  "placements": [
    {
      "idiom_id": "idiom-00204",
      "orientation": "across",
      "row": 0,
      "col": 2
    },
    {
      "idiom_id": "idiom-00421",
      "orientation": "down",
      "row": 0,
      "col": 3
    },
    {
      "idiom_id": "idiom-00493",
      "orientation": "across",
      "row": 3,
      "col": 0
    },
    {
      "idiom_id": "idiom-00492",
      "orientation": "down",
      "row": 3,
      "col": 0
    }
  ]
}